Workbook

Sheet Leeme
A1: Taller 2 – Política Económica (Univalle): crédito, consumo y morosidad en Colombia
A2: Base trimestral 2021-I a 2026-II construida con scripts/construir_base.py a partir de data/raw/.
A4: Hojas
A5: • Base_trimestral: la base del taller (todas las series, incluida la inflación). Fórmulas vivas.
A6: • Ficha_fuentes: entidad, nombre exacto, cobertura, unidad, enlace, fecha de consulta y transformaciones.
A7: • Figuras: las 4 figuras pedidas (título, ejes, unidad, período, fuente y nota).
A8: • Mensual: insumos mensuales transcritos de las fuentes; la TPM mensual se calcula desde TPM_diaria.
A9: • TPM_diaria: serie diaria de la TPM (BanRep) que alimenta el promedio mensual.
A10: • Controles: verifica que los cálculos reproducen los indicadores publicados (SFC, DANE).
A12: Convención de colores
A13: Azul = dato transcrito de la fuente · Negro = fórmula en la misma hoja · Verde = vínculo a otra hoja · Amarillo = parámetro (IPC base).
A15: Decisiones metodológicas (aprobadas por el grupo)
... A22: Pendientes antes de entregar: completar URL exacta y fecha de consulta en Ficha_fuentes; citar la definición de vencimiento de la SFC (Circular Básica Contable y Financiera, Cap. II).

Sheet Base_trimestral
A1: Base trimestral: crédito, consumo y morosidad en Colombia, 2021-I a 2026-II
A2: 2020-IV se incluye solo para calcular la primera variación del consumo. Azul = dato transcrito de la fuente; negro = fórmula; verde = vínculo a otra hoja.
A4: IPC base fijo (jun-2026) | C4: =Mensual!F67 -> 159.53
A6: Trimestre | B6: TPM | C6: Tasa crédito de consumo | D6: Diferencial consumo − TPM | E6: Inflación anual | F6: IPC | G6: Cartera bruta consumo, nominal (B) | H6: Cartera vencida consumo, nominal (V) | I6: Cartera bruta real | J6: Cartera vencida real | K6: Índice cartera bruta real | L6: Índice cartera vencida real | M6: Morosidad (100×V/B) | N6: Consumo final hogares (C) | O6: Índice consumo hogares | P6: Variación trimestral consumo
B7: % e.a., prom. trim. | C7: % e.a., prom. trim. | D7: p.p. | E7: %, último mes | F7: dic-2018=100, último mes | G7: miles de millones $ corrientes | H7: miles de millones $ corrientes | I7: miles de millones $ de jun-2026 | J7: miles de millones $ de jun-2026 | K7: 2021-I = 100 | L7: 2021-I = 100 | M7: % | N7: miles de millones $, volumen ref. 2015, desest. | O7: 2021-I = 100 | P7: %
A8: 2020-IV | N8: 157576.2 | O8: =100*N8/N$9 -> 97.500166
A9: 2021-I | B9: =AVERAGE(Mensual!C2:C4) -> 1.75 | C9: =AVERAGE(Mensual!E2:E4) -> 14.103333 | D9: =C9-B9 -> 12.353333 | E9: =Mensual!G4 -> 1.51 | F9: =Mensual!F4 -> 107.12 | G9: =Mensual!H4 -> 161642.65 | H9: =Mensual!I4 -> 9838.7772 | I9: =G9*$C$4/F9 -> 240728.64 | J9: =H9*$C$4/F9 -> 14652.54 | K9: =100*I9/I$9 -> 100 | L9: =100*J9/J$9 -> 100 | M9: =100*H9/G9 -> 6.0867459 | N9: 161616.34 | O9: =100*N9/N$9 -> 100 | P9: =100*(N9/N8-1) -> 2.5639281
A10: 2021-II | B10: =AVERAGE(Mensual!C5:C7) -> 1.75 | C10: =AVERAGE(Mensual!E5:E7) -> 13.716667 | D10: =C10-B10 -> 11.966667 | E10: =Mensual!G7 -> 3.63 | F10: =Mensual!F7 -> 108.78 | G10: =Mensual!H7 -> 163953.79 | H10: =Mensual!I7 -> 9024.5271 | I10: =G10*$C$4/F10 -> 240444.46 | J10: =H10*$C$4/F10 -> 13234.812 | K10: =100*I10/I$9 -> 99.881952 | L10: =100*J10/J$9 -> 90.324349 | M10: =100*H10/G10 -> 5.5043113 | N10: 158852.47 | O10: =100*N10/N$9 -> 98.289859 | P10: =100*(N10/N9-1) -> -1.710141
A11: 2021-III | B11: =AVERAGE(Mensual!C8:C10) -> 1.75 | C11: =AVERAGE(Mensual!E8:E10) -> 14.34 | D11: =C11-B11 -> 12.59 | E11: =Mensual!G10 -> 4.51 | F11: =Mensual!F10 -> 110.04 | G11: =Mensual!H10 -> 171204.83 | H11: =Mensual!I10 -> 8657.4739 | I11: =G11*$C$4/F11 -> 248203.44 | J11: =H11*$C$4/F11 -> 12551.134 | K11: =100*I11/I$9 -> 103.10508 | L11: =100*J11/J$9 -> 85.658417 | M11: =100*H11/G11 -> 5.0567929 | N11: 168790.19 | O11: =100*N11/N$9 -> 104.43882 | P11: =100*(N11/N10-1) -> 6.2559457
A12: 2021-IV | B12: =AVERAGE(Mensual!C11:C13) -> 2.3922939 | C12: =AVERAGE(Mensual!E11:E13) -> 14.82 | D12: =C12-B12 -> 12.427706 | E12: =Mensual!G13 -> 5.62 | F12: =Mensual!F13 -> 111.41 | G12: =Mensual!H13 -> 180865.69 | H12: =Mensual!I13 -> 8020.8223 | I12: =G12*$C$4/F12 -> 258984.86 | J12: =H12*$C$4/F12 -> 11485.161 | K12: =100*I12/I$9 -> 107.58374 | L12: =100*J12/J$9 -> 78.383411 | M12: =100*H12/G12 -> 4.4346843 | N12: 179579 | O12: =100*N12/N$9 -> 111.11439 | P12: =100*(N12/N11-1) -> 6.3918473
A13: 2022-I | B13: =AVERAGE(Mensual!C14:C16) -> 3.6774194 | C13: =AVERAGE(Mensual!E14:E16) -> 16.73 | D13: =C13-B13 -> 13.052581 | E13: =Mensual!G16 -> 8.53 | F13: =Mensual!F16 -> 116.26 | G13: =Mensual!H16 -> 190568.23 | H13: =Mensual!I16 -> 8391.166 | I13: =G13*$C$4/F13 -> 261494.49 | J13: =H13*$C$4/F13 -> 11514.216 | K13: =100*I13/I$9 -> 108.62625 | L13: =100*J13/J$9 -> 78.581702 | M13: =100*H13/G13 -> 4.4032346 | N13: 181359.54 | O13: =100*N13/N$9 -> 112.21609 | P13: =100*(N13/N12-1) -> 0.99150311
A14: 2022-II | B14: =AVERAGE(Mensual!C17:C19) -> 5.655914 | C14: =AVERAGE(Mensual!E17:E19) -> 19.1 | D14: =C14-B14 -> 13.444086 | E14: =Mensual!G19 -> 9.67 | F14: =Mensual!F19 -> 119.31 | G14: =Mensual!H19 -> 201295.58 | H14: =Mensual!I19 -> 9408.4617 | I14: =G14*$C$4/F14 -> 269153.33 | J14: =H14*$C$4/F14 -> 12580.101 | K14: =100*I14/I$9 -> 111.80777 | L14: =100*J14/J$9 -> 85.856111 | M14: =100*H14/G14 -> 4.6739534 | N14: 184917 | O14: =100*N14/N$9 -> 114.41727 | P14: =100*(N14/N13-1) -> 1.9615513
A15: 2022-III | B15: =AVERAGE(Mensual!C20:C22) -> 8.5111111 | C15: =AVERAGE(Mensual!E20:E22) -> 23.006667 | D15: =C15-B15 -> 14.495556 | E15: =Mensual!G22 -> 11.44 | F15: =Mensual!F22 -> 122.63 | G15: =Mensual!H22 -> 209433.59 | H15: =Mensual!I22 -> 10333.439 | I15: =G15*$C$4/F15 -> 272453.24 | J15: =H15*$C$4/F15 -> 13442.825 | K15: =100*I15/I$9 -> 113.17857 | L15: =100*J15/J$9 -> 91.743986 | M15: =100*H15/G15 -> 4.9339933 | N15: 186877.93 | O15: =100*N15/N$9 -> 115.6306 | P15: =100*(N15/N14-1) -> 1.0604408
A16: 2022-IV | B16: =AVERAGE(Mensual!C23:C25) -> 10.817204 | C16: =AVERAGE(Mensual!E23:E25) -> 27.266667 | D16: =C16-B16 -> 16.449462 | E16: =Mensual!G25 -> 13.12 | F16: =Mensual!F25 -> 126.03 | G16: =Mensual!H25 -> 213945.76 | H16: =Mensual!I25 -> 11777.185 | I16: =G16*$C$4/F16 -> 270814.62 | J16: =H16*$C$4/F16 -> 14907.675 | K16: =100*I16/I$9 -> 112.49788 | L16: =100*J16/J$9 -> 101.74123 | M16: =100*H16/G16 -> 5.5047525 | N16: 187849.54 | O16: =100*N16/N$9 -> 116.23178 | P16: =100*(N16/N15-1) -> 0.51991588
A17: 2023-I | B17: =AVERAGE(Mensual!C26:C28) -> 12.518817 | C17: =AVERAGE(Mensual!E26:E28) -> 30.16 | D17: =C17-B17 -> 17.641183 | E17: =Mensual!G28 -> 13.34 | F17: =Mensual!F28 -> 131.77 | G17: =Mensual!H28 -> 213106.83 | H17: =Mensual!I28 -> 14370.308 | I17: =G17*$C$4/F17 -> 258002.07 | J17: =H17*$C$4/F17 -> 17397.702 | K17: =100*I17/I$9 -> 107.17548 | L17: =100*J17/J$9 -> 118.73506 | M17: =100*H17/G17 -> 6.7432412 | N17: 186443.13 | O17: =100*N17/N$9 -> 115.36157 | P17: =100*(N17/N16-1) -> -0.74868653
A18: 2023-II | B18: =AVERAGE(Mensual!C29:C31) -> 13.163978 | C18: =AVERAGE(Mensual!E29:E31) -> 28.543333 | D18: =C18-B18 -> 15.379355 | E18: =Mensual!G31 -> 12.13 | F18: =Mensual!F31 -> 133.78 | G18: =Mensual!H31 -> 211899.67 | H18: =Mensual!I31 -> 15974.106 | I18: =G18*$C$4/F18 -> 252686.16 | J18: =H18*$C$4/F18 -> 19048.805 | K18: =100*I18/I$9 -> 104.96722 | L18: =100*J18/J$9 -> 130.00343 | M18: =100*H18/G18 -> 7.5385236 | N18: 186036.47 | O18: =100*N18/N$9 -> 115.10994 | P18: =100*(N18/N17-1) -> -0.21811521
A19: 2023-III | B19: =AVERAGE(Mensual!C32:C34) -> 13.25 | C19: =AVERAGE(Mensual!E32:E34) -> 26.796667 | D19: =C19-B19 -> 13.546667 | E19: =Mensual!G34 -> 10.99 | F19: =Mensual!F34 -> 136.11 | G19: =Mensual!H34 -> 211082.01 | H19: =Mensual!I34 -> 16431.637 | I19: =G19*$C$4/F19 -> 247402.2 | J19: =H19*$C$4/F19 -> 19258.975 | K19: =100*I19/I$9 -> 102.77223 | L19: =100*J19/J$9 -> 131.43778 | M19: =100*H19/G19 -> 7.78448 | N19: 185876.14 | O19: =100*N19/N$9 -> 115.01074 | P19: =100*(N19/N18-1) -> -0.086184696
A20: 2023-IV | B20: =AVERAGE(Mensual!C35:C37) -> 13.217742 | C20: =AVERAGE(Mensual!E35:E37) -> 26.313333 | D20: =C20-B20 -> 13.095591 | E20: =Mensual!G37 -> 9.28 | F20: =Mensual!F37 -> 137.72 | G20: =Mensual!H37 -> 208832.58 | H20: =Mensual!I37 -> 17183.372 | I20: =G20*$C$4/F20 -> 241904.31 | J20: =H20*$C$4/F20 -> 19904.613 | K20: =100*I20/I$9 -> 100.48838 | L20: =100*J20/J$9 -> 135.84411 | M20: =100*H20/G20 -> 8.2283 | N20: 186451.25 | O20: =100*N20/N$9 -> 115.36659 | P20: =100*(N20/N19-1) -> 0.30940728
A21: 2024-I | B21: =AVERAGE(Mensual!C38:C40) -> 12.801075 | C21: =AVERAGE(Mensual!E38:E40) -> 23.94 | D21: =C21-B21 -> 11.138925 | E21: =Mensual!G40 -> 7.36 | F21: =Mensual!F40 -> 141.48 | G21: =Mensual!H40 -> 204330.78 | H21: =Mensual!I40 -> 17198.915 | I21: =G21*$C$4/F21 -> 230399.28 | J21: =H21*$C$4/F21 -> 19393.15 | K21: =100*I21/I$9 -> 95.709128 | L21: =100*J21/J$9 -> 132.3535 | M21: =100*H21/G21 -> 8.417192 | N21: 186671.52 | O21: =100*N21/N$9 -> 115.50288 | P21: =100*(N21/N20-1) -> 0.11813541
A22: 2024-II | B22: =AVERAGE(Mensual!C41:C43) -> 11.922043 | C22: =AVERAGE(Mensual!E41:E43) -> 22.496667 | D22: =C22-B22 -> 10.574624 | E22: =Mensual!G43 -> 7.18 | F22: =Mensual!F43 -> 143.38 | G22: =Mensual!H43 -> 201839.19 | H22: =Mensual!I43 -> 16309.535 | I22: =G22*$C$4/F22 -> 224573.91 | J22: =H22*$C$4/F22 -> 18146.604 | K22: =100*I22/I$9 -> 93.289236 | L22: =100*J22/J$9 -> 123.84613 | M22: =100*H22/G22 -> 8.0804596 | N22: 188642.53 | O22: =100*N22/N$9 -> 116.72244 | P22: =100*(N22/N21-1) -> 1.0558717
A23: 2024-III | B23: =AVERAGE(Mensual!C44:C46) -> 10.922043 | C23: =AVERAGE(Mensual!E44:E46) -> 21.186667 | D23: =C23-B23 -> 10.264624 | E23: =Mensual!G46 -> 5.81 | F23: =Mensual!F46 -> 144.02 | G23: =Mensual!H46 -> 200430.44 | H23: =Mensual!I46 -> 15246.242 | I23: =G23*$C$4/F23 -> 222015.47 | J23: =H23*$C$4/F23 -> 16888.161 | K23: =100*I23/I$9 -> 92.226449 | L23: =100*J23/J$9 -> 115.25756 | M23: =100*H23/G23 -> 7.6067497 | N23: 189804.89 | O23: =100*N23/N$9 -> 117.44165 | P23: =100*(N23/N22-1) -> 0.61617252
A24: 2024-IV | B24: =AVERAGE(Mensual!C47:C49) -> 9.8924731 | C24: =AVERAGE(Mensual!E47:E49) -> 20.03 | D24: =C24-B24 -> 10.137527 | E24: =Mensual!G49 -> 5.2 | F24: =Mensual!F49 -> 144.88 | G24: =Mensual!H49 -> 202124.39 | H24: =Mensual!I49 -> 13992.201 | I24: =G24*$C$4/F24 -> 222562.84 | J24: =H24*$C$4/F24 -> 15407.067 | K24: =100*I24/I$9 -> 92.453827 | L24: =100*J24/J$9 -> 105.14946 | M24: =100*H24/G24 -> 6.9225694 | N24: 191904.06 | O24: =100*N24/N$9 -> 118.74051 | P24: =100*(N24/N23-1) -> 1.1059599
A25: 2025-I | B25: =AVERAGE(Mensual!C50:C52) -> 9.5 | C25: =AVERAGE(Mensual!E50:E52) -> 19.466667 | D25: =C25-B25 -> 9.9666667 | E25: =Mensual!G52 -> 5.09 | F25: =Mensual!F52 -> 148.68 | G25: =Mensual!H52 -> 201289.12 | H25: =Mensual!I52 -> 13184.57 | I25: =G25*$C$4/F25 -> 215978.3 | J25: =H25*$C$4/F25 -> 14146.721 | K25: =100*I25/I$9 -> 89.718575 | L25: =100*J25/J$9 -> 96.547906 | M25: =100*H25/G25 -> 6.5500659 | N25: 194998.98 | O25: =100*N25/N$9 -> 120.65549 | P25: =100*(N25/N24-1) -> 1.6127426
A26: 2025-II | B26: =AVERAGE(Mensual!C53:C55) -> 9.3360215 | C26: =AVERAGE(Mensual!E53:E55) -> 19.286667 | D26: =C26-B26 -> 9.9506452 | E26: =Mensual!G55 -> 4.82 | F26: =Mensual!F55 -> 150.3 | G26: =Mensual!H55 -> 204000.6 | H26: =Mensual!I55 -> 12192.612 | I26: =G26*$C$4/F26 -> 216528.38 | J26: =H26*$C$4/F26 -> 12941.366 | K26: =100*I26/I$9 -> 89.94708 | L26: =100*J26/J$9 -> 88.321656 | M26: =100*H26/G26 -> 5.976753 | N26: 195404.43 | O26: =100*N26/N$9 -> 120.90636 | P26: =100*(N26/N25-1) -> 0.20792784
A27: 2025-III | B27: =AVERAGE(Mensual!C56:C58) -> 9.25 | C27: =AVERAGE(Mensual!E56:E58) -> 18.85 | D27: =C27-B27 -> 9.6 | E27: =Mensual!G58 -> 5.18 | F27: =Mensual!F58 -> 151.48 | G27: =Mensual!H58 -> 209338.98 | H27: =Mensual!I58 -> 11252.699 | I27: =G27*$C$4/F27 -> 220463.74 | J27: =H27*$C$4/F27 -> 11850.694 | K27: =100*I27/I$9 -> 91.581849 | L27: =100*J27/J$9 -> 80.878085 | M27: =100*H27/G27 -> 5.3753485 | N27: 197023.36 | O27: =100*N27/N$9 -> 121.90807 | P27: =100*(N27/N26-1) -> 0.8284974
A28: 2025-IV | B28: =AVERAGE(Mensual!C59:C61) -> 9.25 | C28: =AVERAGE(Mensual!E59:E61) -> 18.983333 | D28: =C28-B28 -> 9.7333333 | E28: =Mensual!G61 -> 5.1 | F28: =Mensual!F61 -> 152.27 | G28: =Mensual!H61 -> 215901.95 | H28: =Mensual!I61 -> 10804.101 | I28: =G28*$C$4/F28 -> 226195.82 | J28: =H28*$C$4/F28 -> 11319.224 | K28: =100*I28/I$9 -> 93.962988 | L28: =100*J28/J$9 -> 77.250932 | M28: =100*H28/G28 -> 5.0041703 | N28: 196198.96 | O28: =100*N28/N$9 -> 121.39797 | P28: =100*(N28/N27-1) -> -0.41842609
A29: 2026-I | B29: =AVERAGE(Mensual!C62:C64) -> 9.9047619 | C29: =AVERAGE(Mensual!E62:E64) -> 19.953333 | D29: =C29-B29 -> 10.048571 | E29: =Mensual!G64 -> 5.56 | F29: =Mensual!F64 -> 156.94 | G29: =Mensual!H64 -> 219666.7 | H29: =Mensual!I64 -> 11024.834 | I29: =G29*$C$4/F29 -> 223291.89 | J29: =H29*$C$4/F29 -> 11206.778 | K29: =100*I29/I$9 -> 92.756678 | L29: =100*J29/J$9 -> 76.483519 | M29: =100*H29/G29 -> 5.018892 | N29: 199985.29 | O29: =100*N29/N$9 -> 123.74077 | P29: =100*(N29/N28-1) -> 1.9298447
A30: 2026-II | B30: =AVERAGE(Mensual!C65:C67) -> 11.25 | C30: =AVERAGE(Mensual!E65:E67) -> 21.413333 | D30: =C30-B30 -> 10.163333 | E30: =Mensual!G67 -> 6.14 | F30: =Mensual!F67 -> 159.53 | G30: =Mensual!H67 -> 224646.11 | H30: =Mensual!I67 -> 11187.692 | I30: =G30*$C$4/F30 -> 224646.11 | J30: =H30*$C$4/F30 -> 11187.692 | K30: =100*I30/I$9 -> 93.319232 | L30: =100*J30/J$9 -> 76.353255 | M30: =100*H30/G30 -> 4.9801402 | N30: 200930.49 | O30: =100*N30/N$9 -> 124.3256 | P30: =100*(N30/N29-1) -> 0.47263087
A32: Notas metodológicas:
A33: • Tasas: TPM = promedio de la serie diaria por mes y luego de los 3 meses; tasa de consumo = promedio de las 3 tasas mensuales (créditos nuevos, no incluye tarjetas). Ambas en % efectivo anual.
A34: • Cartera: saldo del último mes de cada trimestre (SFC, hoja C5), establecimientos de crédito sin IOE, incluye leasing. No se suman saldos mensuales. Vencida ≠ riesgosa (calificación B-E) ≠ provisiones (deterioro).
A35: • Real = nominal × IPC(jun-2026) / IPC(mes del saldo). Morosidad = 100 × V / B (con saldos nominales; es igual con reales porque el deflactor se cancela).
A36: • Consumo: gasto de consumo final de los hogares incluidas ISFLSH, volumen, desestacionalizado; no se deflacta de nuevo. 2020-IV solo alimenta la variación de 2021-I.
A37: • Limitación de cobertura: la cartera SFC incluye tarjetas de crédito; la tasa de consumo BanRep no. Para crédito y morosidad se prioriza la SFC.
A38: • Sin datos faltantes en la ventana 2021-I a 2026-II: no hubo que dejar celdas vacías ni interpolar.

Sheet Ficha_fuentes
A1: Ficha de fuentes
A2: Los campos entre corchetes [ ] deben completarse con la URL exacta y la fecha en que se consultó cada fuente; no se inventan.
A4: Variable | B4: Entidad | C4: Nombre exacto de la serie | D4: Cobertura | E4: Unidad | F4: Frecuencia y período | G4: Archivo original (data/raw) | H4: Enlace | I4: Fecha de consulta | J4: Transformaciones
A5: Tasa de intervención (TPM) | B5: Banco de la República | C5: Tasa de política monetaria (Dato diario) | D5: Tasa mínima de las subastas de expansión a un día (OMA) | E5: % (efectivo anual) | F5: Diaria, 01/01/2021–30/06/2026 | G5: Datos_Adicionales_BANREP.xlsx, hoja Datos | H5: https://www.banrep.gov.co/es/estadisticas [pegar la URL exacta de la consulta] | I5: 16-oct-2026 (pie del archivo) | J5: Promedio simple de los días de cada mes → promedio simple de los 3 meses del trimestre.
A6: Tasa del crédito de consumo | B6: Banco de la República con información de la SFC | C6: Crédito de consumo, Tasa de interés (Promedio mensual) | D6: Créditos de consumo desembolsados; no incluye tarjetas de crédito | E6: % efectivo anual | F6: Mensual, ene-2021–jun-2026 | G6: Datos_Adicionales_BANREP.xlsx, hoja Datos | H6: https://www.banrep.gov.co/es/estadisticas [pegar la URL exacta de la consulta] | I6: 16-oct-2026 (pie del archivo) | J6: Promedio simple de las 3 tasas mensuales del trimestre.
A7: Cartera bruta de consumo (B) | B7: Superintendencia Financiera de Colombia | C7: Evolución de la cartera de crédito por tipo de crédito — CONSUMO - BRUTA (hoja C5) | D7: Establecimientos de crédito, sin Instituciones Oficiales Especiales; incluye leasing | E7: Miles de millones de pesos corrientes (el título de C5 dice 'millones'; C5 suma exactamente C4, rotulada en miles de millones) | F7: Mensual, ene-2016–ago-2026; se usan mar/jun/sep/dic 2021-2026 | G7: Cartera_hasta_agosto_Superfinanciera.xlsx, hoja C5 | H7: https://www.superfinanciera.gov.co (Evolución de la cartera de créditos) [pegar la URL exacta] | I7: [completar]; cifras reportadas al 25-sep-2026 | J7: Saldo del último mes del trimestre. Real = B × IPC(jun-2026) / IPC(mes). Índice = 100 × real / real(2021-I).
A8: Cartera vencida de consumo (V) | B8: Superintendencia Financiera de Colombia | C8: CONSUMO - VENCIDA (hoja C5) | D8: Igual a la cartera bruta (misma hoja y cobertura) | E8: Miles de millones de pesos corrientes | F8: Mensual; se usan mar/jun/sep/dic 2021-2026 | G8: Cartera_hasta_agosto_Superfinanciera.xlsx, hoja C5 | H8: https://www.superfinanciera.gov.co [pegar la URL exacta] | I8: [completar]; cifras reportadas al 25-sep-2026 | J8: Vencimiento: mora > 30 días (criterio SFC; confirmar en la Circular Básica Contable y Financiera, Cap. II). No se usa DETERIORO (provisiones) ni calidad por calificación (cartera riesgosa B-E). Real e índice igual que B. Morosidad = 100 × V / B.
A9: Consumo final de los hogares (C) | B9: DANE | C9: Gasto de consumo final individual de los hogares; gasto de consumo final de las ISFLSH (P.311 + P.313 + P.323), Cuadro 2 | D9: Total nacional; incluye ISFLSH; excluye Gobierno | E9: Miles de millones de pesos, series encadenadas de volumen, año de referencia 2015; ajustada por efecto estacional y calendario | F9: Trimestral, 2020-IV–2026-II (2024p provisional; 2025-2026pr preliminar) | G9: anex-GastoConstantes-IItrim2026.xlsx, Cuadro 2 | H9: https://www.dane.gov.co (Cuentas nacionales trimestrales, PIB enfoque del gasto) [pegar la URL exacta] | I9: [completar]; anexo actualizado el 18-ago-2026 | J9: No se deflacta. Índice = 100 × C / C(2021-I). Variación trimestral = 100 × (C_t / C_t-1 − 1).
A10: IPC (deflactor) | B10: DANE (vía Banco de la República) | C10: Índice de Precios al Consumidor (IPC) (Dato fin de mes) | D10: Total nacional | E10: Índice, base dic-2018 = 100 | F10: Mensual, ene-2021–jun-2026 | G10: Datos_BANREP_2.xlsx, hoja Datos | H10: https://www.banrep.gov.co/es/estadisticas [pegar la URL exacta] | I10: 16-oct-2026 (pie del archivo) | J10: IPC del último mes de cada trimestre. IPC base fijo = jun-2026 (159,53).
A11: Inflación anual | B11: DANE (vía Banco de la República) | C11: Índice de Precios al Consumidor (IPC) (Variación porcentual anual) | D11: Total nacional | E11: % (variación a 12 meses) | F11: Mensual, ene-2021–jun-2026 | G11: Datos_BANREP_2.xlsx, hoja Datos | H11: https://www.banrep.gov.co/es/estadisticas [pegar la URL exacta] | I11: 16-oct-2026 (pie del archivo) | J11: Dato del último mes de cada trimestre (mar, jun, sep, dic). Idéntica a 'Inflación total anual'.

Sheet Figuras
A1: Figuras del taller (también en output/figuras/*.png)

Sheet TPM_diaria
A1: Fecha | B1: TPM diaria (%)
A2: 44197 | B2: 1.75
A3: 44198 | B3: 1.75
A4: 44199 | B4: 1.75
A5: 44200 | B5: 1.75
A6: 44201 | B6: 1.75
A7: 44202 | B7: 1.75
A8: 44203 | B8: 1.75
A9: 44204 | B9: 1.75
A10: 44205 | B10: 1.75
A11: 44206 | B11: 1.75
A12: 44207 | B12: 1.75
A13: 44208 | B13: 1.75
... A2008: 46203 | B2008: 11.25

Sheet Mensual
A1: Mes | B1: Trimestre | C1: TPM, promedio diario del mes (%) | D1: TPM 'Dato mes' BanRep (%) [control] | E1: Tasa crédito de consumo, prom. mensual (% e.a.) | F1: IPC (dic-2018=100) | G1: Inflación anual (%) | H1: Cartera bruta consumo (miles de millones $) | I1: Cartera vencida consumo (miles de millones $) | J1: Indicador calidad tradicional consumo SFC (fracción) [control]
A2: 44197 | B2: 2021-I | C2: =AVERAGEIFS(TPM_diaria!$B$2:$B$2008,TPM_diaria!$A$2:$A$2008,">="&A2,TPM_diaria!$A$2:$A$2008,"<="&EOMONTH(A2,0)) -> 1.75 | D2: 1.75 | E2: 14.69 | F2: 105.91 | G2: 1.6 | H2: 159942.78 | I2: 10525.283 | J2: 0.065807
A3: 44228 | B3: 2021-I | C3: =AVERAGEIFS(TPM_diaria!$B$2:$B$2008,TPM_diaria!$A$2:$A$2008,">="&A3,TPM_diaria!$A$2:$A$2008,"<="&EOMONTH(A3,0)) -> 1.75 | D3: 1.75 | E3: 13.96 | F3: 106.58 | G3: 1.56 | H3: 160803.37 | I3: 10360.188 | J3: 0.064428
A4: 44256 | B4: 2021-I | C4: =AVERAGEIFS(TPM_diaria!$B$2:$B$2008,TPM_diaria!$A$2:$A$2008,">="&A4,TPM_diaria!$A$2:$A$2008,"<="&EOMONTH(A4,0)) -> 1.75 | D4: 1.75 | E4: 13.66 | F4: 107.12 | G4: 1.51 | H4: 161642.65 | I4: 9838.7772 | J4: 0.060867
A5: 44287 | B5: 2021-II | C5: =AVERAGEIFS(TPM_diaria!$B$2:$B$2008,TPM_diaria!$A$2:$A$2008,">="&A5,TPM_diaria!$A$2:$A$2008,"<="&EOMONTH(A5,0)) -> 1.75 | D5: 1.75 | E5: 13.55 | F5: 107.76 | G5: 1.95 | H5: 162332.15 | I5: 9783.326 | J5: 0.060267
A6: 44317 | B6: 2021-II | C6: =AVERAGEIFS(TPM_diaria!$B$2:$B$2008,TPM_diaria!$A$2:$A$2008,">="&A6,TPM_diaria!$A$2:$A$2008,"<="&EOMONTH(A6,0)) -> 1.75 | D6: 1.75 | E6: 13.7 | F6: 108.84 | G6: 3.3 | H6: 162574.08 | I6: 9368.9502 | J6: 0.057629
A7: 44348 | B7: 2021-II | C7: =AVERAGEIFS(TPM_diaria!$B$2:$B$2008,TPM_diaria!$A$2:$A$2008,">="&A7,TPM_diaria!$A$2:$A$2008,"<="&EOMONTH(A7,0)) -> 1.75 | D7: 1.75 | E7: 13.9 | F7: 108.78 | G7: 3.63 | H7: 163953.79 | I7: 9024.5271 | J7: 0.055043
A8: 44378 | B8: 2021-III | C8: =AVERAGEIFS(TPM_diaria!$B$2:$B$2008,TPM_diaria!$A$2:$A$2008,">="&A8,TPM_diaria!$A$2:$A$2008,"<="&EOMONTH(A8,0)) -> 1.75 | D8: 1.75 | E8: 14.28 | F8: 109.14 | G8: 3.97 | H8: 165796.09 | I8: 8859.1323 | J8: 0.053434
A9: 44409 | B9: 2021-III | C9: =AVERAGEIFS(TPM_diaria!$B$2:$B$2008,TPM_diaria!$A$2:$A$2008,">="&A9,TPM_diaria!$A$2:$A$2008,"<="&EOMONTH(A9,0)) -> 1.75 | D9: 1.75 | E9: 14.38 | F9: 109.62 | G9: 4.44 | H9: 168246.1 | I9: 8700.1569 | J9: 0.051711
A10: 44440 | B10: 2021-III | C10: =AVERAGEIFS(TPM_diaria!$B$2:$B$2008,TPM_diaria!$A$2:$A$2008,">="&A10,TPM_diaria!$A$2:$A$2008,"<="&EOMONTH(A10,0)) -> 1.75 | D10: 1.75 | E10: 14.36 | F10: 110.04 | G10: 4.51 | H10: 171204.83 | I10: 8657.4739 | J10: 0.050568
A11: 44470 | B11: 2021-IV | C11: =AVERAGEIFS(TPM_diaria!$B$2:$B$2008,TPM_diaria!$A$2:$A$2008,">="&A11,TPM_diaria!$A$2:$A$2008,"<="&EOMONTH(A11,0)) -> 2 | D11: 2 | E11: 14.42 | F11: 110.06 | G11: 4.58 | H11: 174454.66 | I11: 8584.6647 | J11: 0.049209
A12: 44501 | B12: 2021-IV | C12: =AVERAGEIFS(TPM_diaria!$B$2:$B$2008,TPM_diaria!$A$2:$A$2008,">="&A12,TPM_diaria!$A$2:$A$2008,"<="&EOMONTH(A12,0)) -> 2.4833333 | D12: 2.5 | E12: 14.86 | F12: 110.6 | G12: 5.26 | H12: 178424.63 | I12: 8543.2616 | J12: 0.047882
A13: 44531 | B13: 2021-IV | C13: =AVERAGEIFS(TPM_diaria!$B$2:$B$2008,TPM_diaria!$A$2:$A$2008,">="&A13,TPM_diaria!$A$2:$A$2008,"<="&EOMONTH(A13,0)) -> 2.6935484 | D13: 2.5 | E13: 15.18 | F13: 111.41 | G13: 5.62 | H13: 180865.69 | I13: 8020.8223 | J13: 0.044347
... A67: 46174 | B67: 2026-II | C67: =AVERAGEIFS(TPM_diaria!$B$2:$B$2008,TPM_diaria!$A$2:$A$2008,">="&A67,TPM_diaria!$A$2:$A$2008,"<="&EOMONTH(A67,0)) -> 11.25 | D67: 11.25 | E67: 21.85 | F67: 159.53 | G67: 6.14 | H67: 224646.11 | I67: 11187.692 | J67: 0.049801

Sheet Controles
A1: Controles de cálculo (diferencias ≈ 0 confirman que las fórmulas reproducen las fuentes)
A3: Trimestre | B3: Morosidad propia (%) | C3: Indicador SFC × 100 (%) | D3: Diferencia | E3: Var. trim. consumo propia (%) | F3: Var. trim. publicada DANE (%) | G3: Diferencia | H3: TPM prom. diario (%) | I3: TPM 'Dato mes' prom. (%) | J3: Diferencia (p.p.)
A4: 2021-I | B4: =Base_trimestral!M9 -> 6.0867459 | C4: =100*Mensual!J4 -> 6.0867 | D4: =B4-C4 -> 4.5906938e-05 | E4: =Base_trimestral!P9 -> 2.5639281 | F4: 2.5639281 | G4: =E4-F4 -> 0 | H4: =Base_trimestral!B9 -> 1.75 | I4: =AVERAGE(Mensual!D2:D4) -> 1.75 | J4: =H4-I4 -> 0
A5: 2021-II | B5: =Base_trimestral!M10 -> 5.5043113 | C5: =100*Mensual!J7 -> 5.5043 | D5: =B5-C5 -> 1.1317052e-05 | E5: =Base_trimestral!P10 -> -1.710141 | F5: -1.710141 | G5: =E5-F5 -> 0 | H5: =Base_trimestral!B10 -> 1.75 | I5: =AVERAGE(Mensual!D5:D7) -> 1.75 | J5: =H5-I5 -> 0
A6: 2021-III | B6: =Base_trimestral!M11 -> 5.0567929 | C6: =100*Mensual!J10 -> 5.0568 | D6: =B6-C6 -> -7.0606524e-06 | E6: =Base_trimestral!P11 -> 6.2559457 | F6: 6.2559457 | G6: =E6-F6 -> 0 | H6: =Base_trimestral!B11 -> 1.75 | I6: =AVERAGE(Mensual!D8:D10) -> 1.75 | J6: =H6-I6 -> 0
A7: 2021-IV | B7: =Base_trimestral!M12 -> 4.4346843 | C7: =100*Mensual!J13 -> 4.4347 | D7: =B7-C7 -> -1.5674962e-05 | E7: =Base_trimestral!P12 -> 6.3918473 | F7: 6.3918473 | G7: =E7-F7 -> 0 | H7: =Base_trimestral!B12 -> 2.3922939 | I7: =AVERAGE(Mensual!D11:D13) -> 2.3333333 | J7: =H7-I7 -> 0.058960573
A8: 2022-I | B8: =Base_trimestral!M13 -> 4.4032346 | C8: =100*Mensual!J16 -> 4.4032 | D8: =B8-C8 -> 3.458543e-05 | E8: =Base_trimestral!P13 -> 0.99150311 | F8: 0.99150311 | G8: =E8-F8 -> 0 | H8: =Base_trimestral!B13 -> 3.6774194 | I8: =AVERAGE(Mensual!D14:D16) -> 3.6666667 | J8: =H8-I8 -> 0.010752688
A9: 2022-II | B9: =Base_trimestral!M14 -> 4.6739534 | C9: =100*Mensual!J19 -> 4.674 | D9: =B9-C9 -> -4.6551486e-05 | E9: =Base_trimestral!P14 -> 1.9615513 | F9: 1.9615513 | G9: =E9-F9 -> 0 | H9: =Base_trimestral!B14 -> 5.655914 | I9: =AVERAGE(Mensual!D17:D19) -> 5.6666667 | J9: =H9-I9 -> -0.010752688
A10: 2022-III | B10: =Base_trimestral!M15 -> 4.9339933 | C10: =100*Mensual!J22 -> 4.934 | D10: =B10-C10 -> -6.6939674e-06 | E10: =Base_trimestral!P15 -> 1.0604408 | F10: 1.0604408 | G10: =E10-F10 -> 0 | H10: =Base_trimestral!B15 -> 8.5111111 | I10: =AVERAGE(Mensual!D20:D22) -> 8.5 | J10: =H10-I10 -> 0.011111111
A11: 2022-IV | B11: =Base_trimestral!M16 -> 5.5047525 | C11: =100*Mensual!J25 -> 5.5048 | D11: =B11-C11 -> -4.7474071e-05 | E11: =Base_trimestral!P16 -> 0.51991588 | F11: 0.51991588 | G11: =E11-F11 -> -5.3290705e-15 | H11: =Base_trimestral!B16 -> 10.817204 | I11: =AVERAGE(Mensual!D23:D25) -> 10.666667 | J11: =H11-I11 -> 0.15053763
A12: 2023-I | B12: =Base_trimestral!M17 -> 6.7432412 | C12: =100*Mensual!J28 -> 6.7432 | D12: =B12-C12 -> 4.121587e-05 | E12: =Base_trimestral!P17 -> -0.74868653 | F12: -0.74868653 | G12: =E12-F12 -> 3.5527137e-15 | H12: =Base_trimestral!B17 -> 12.518817 | I12: =AVERAGE(Mensual!D26:D28) -> 12.5 | J12: =H12-I12 -> 0.018817204
A13: 2023-II | B13: =Base_trimestral!M18 -> 7.5385236 | C13: =100*Mensual!J31 -> 7.5385 | D13: =B13-C13 -> 2.3555107e-05 | E13: =Base_trimestral!P18 -> -0.21811521 | F13: -0.21811521 | G13: =E13-F13 -> 9.15934e-16 | H13: =Base_trimestral!B18 -> 13.163978 | I13: =AVERAGE(Mensual!D29:D31) -> 13.166667 | J13: =H13-I13 -> -0.002688172
A14: 2023-III | B14: =Base_trimestral!M19 -> 7.78448 | C14: =100*Mensual!J34 -> 7.7845 | D14: =B14-C14 -> -2.0044491e-05 | E14: =Base_trimestral!P19 -> -0.086184696 | F14: -0.086184696 | G14: =E14-F14 -> 1.7763568e-15 | H14: =Base_trimestral!B19 -> 13.25 | I14: =AVERAGE(Mensual!D32:D34) -> 13.25 | J14: =H14-I14 -> 0
A15: 2023-IV | B15: =Base_trimestral!M20 -> 8.2283 | C15: =100*Mensual!J37 -> 8.2283 | D15: =B15-C15 -> 3.6577751e-08 | E15: =Base_trimestral!P20 -> 0.30940728 | F15: 0.30940728 | G15: =E15-F15 -> -2.7200464e-15 | H15: =Base_trimestral!B20 -> 13.217742 | I15: =AVERAGE(Mensual!D35:D37) -> 13.25 | J15: =H15-I15 -> -0.032258065
A16: 2024-I | B16: =Base_trimestral!M21 -> 8.417192 | C16: =100*Mensual!J40 -> 8.4172 | D16: =B16-C16 -> -7.9641197e-06 | E16: =Base_trimestral!P21 -> 0.11813541 | F16: 0.11813541 | G16: =E16-F16 -> 3.594347e-15 | H16: =Base_trimestral!B21 -> 12.801075 | I16: =AVERAGE(Mensual!D38:D40) -> 12.833333 | J16: =H16-I16 -> -0.032258065
A17: 2024-II | B17: =Base_trimestral!M22 -> 8.0804596 | C17: =100*Mensual!J43 -> 8.0805 | D17: =B17-C17 -> -4.0387902e-05 | E17: =Base_trimestral!P22 -> 1.0558717 | F17: 1.0558717 | G17: =E17-F17 -> 4.6629367e-15 | H17: =Base_trimestral!B22 -> 11.922043 | I17: =AVERAGE(Mensual!D41:D43) -> 11.916667 | J17: =H17-I17 -> 0.0053763441
A18: 2024-III | B18: =Base_trimestral!M23 -> 7.6067497 | C18: =100*Mensual!J46 -> 7.6067 | D18: =B18-C18 -> 4.9650884e-05 | E18: =Base_trimestral!P23 -> 0.61617252 | F18: 0.61617252 | G18: =E18-F18 -> 0 | H18: =Base_trimestral!B23 -> 10.922043 | I18: =AVERAGE(Mensual!D44:D46) -> 10.916667 | J18: =H18-I18 -> 0.0053763441
A19: 2024-IV | B19: =Base_trimestral!M24 -> 6.9225694 | C19: =100*Mensual!J49 -> 6.9226 | D19: =B19-C19 -> -3.055696e-05 | E19: =Base_trimestral!P24 -> 1.1059599 | F19: 1.1059599 | G19: =E19-F19 -> 4.2188475e-15 | H19: =Base_trimestral!B24 -> 9.8924731 | I19: =AVERAGE(Mensual!D47:D49) -> 9.9166667 | J19: =H19-I19 -> -0.024193548
A20: 2025-I | B20: =Base_trimestral!M25 -> 6.5500659 | C20: =100*Mensual!J52 -> 6.5501 | D20: =B20-C20 -> -3.4136294e-05 | E20: =Base_trimestral!P25 -> 1.6127426 | F20: 1.6127426 | G20: =E20-F20 -> 0 | H20: =Base_trimestral!B25 -> 9.5 | I20: =AVERAGE(Mensual!D50:D52) -> 9.5 | J20: =H20-I20 -> 0
A21: 2025-II | B21: =Base_trimestral!M26 -> 5.976753 | C21: =100*Mensual!J55 -> 5.9768 | D21: =B21-C21 -> -4.699344e-05 | E21: =Base_trimestral!P26 -> 0.20792784 | F21: 0.20792784 | G21: =E21-F21 -> 4.4686477e-15 | H21: =Base_trimestral!B26 -> 9.3360215 | I21: =AVERAGE(Mensual!D53:D55) -> 9.3333333 | J21: =H21-I21 -> 0.002688172
A22: 2025-III | B22: =Base_trimestral!M27 -> 5.3753485 | C22: =100*Mensual!J58 -> 5.3753 | D22: =B22-C22 -> 4.8450976e-05 | E22: =Base_trimestral!P27 -> 0.8284974 | F22: 0.8284974 | G22: =E22-F22 -> -5.3290705e-15 | H22: =Base_trimestral!B27 -> 9.25 | I22: =AVERAGE(Mensual!D56:D58) -> 9.25 | J22: =H22-I22 -> 0
A23: 2025-IV | B23: =Base_trimestral!M28 -> 5.0041703 | C23: =100*Mensual!J61 -> 5.0042 | D23: =B23-C23 -> -2.9668038e-05 | E23: =Base_trimestral!P28 -> -0.41842609 | F23: -0.41842609 | G23: =E23-F23 -> 0 | H23: =Base_trimestral!B28 -> 9.25 | I23: =AVERAGE(Mensual!D59:D61) -> 9.25 | J23: =H23-I23 -> 0
A24: 2026-I | B24: =Base_trimestral!M29 -> 5.018892 | C24: =100*Mensual!J64 -> 5.0189 | D24: =B24-C24 -> -8.0429411e-06 | E24: =Base_trimestral!P29 -> 1.9298447 | F24: 1.9298447 | G24: =E24-F24 -> 0 | H24: =Base_trimestral!B29 -> 9.9047619 | I24: =AVERAGE(Mensual!D62:D64) -> 9.9166667 | J24: =H24-I24 -> -0.011904762
A25: 2026-II | B25: =Base_trimestral!M30 -> 4.9801402 | C25: =100*Mensual!J67 -> 4.9801 | D25: =B25-C25 -> 4.022712e-05 | E25: =Base_trimestral!P30 -> 0.47263087 | F25: 0.47263087 | G25: =E25-F25 -> -5.3290705e-15 | H25: =Base_trimestral!B30 -> 11.25 | I25: =AVERAGE(Mensual!D65:D67) -> 11.25 | J25: =H25-I25 -> 0
A27: Máx. |dif.| | D27: =MAX(MAX(D4:D25),-MIN(D4:D25)) -> 4.9650884e-05 | G27: =MAX(MAX(G4:G25),-MIN(G4:G25)) -> 5.3290705e-15 | J27: =MAX(MAX(J4:J25),-MIN(J4:J25)) -> 0.15053763
A29: D: el indicador SFC viene redondeado a 6 decimales (fracción), por eso la diferencia es del orden de 0,0001 p.p. G: la variación publicada por el DANE en el Cuadro 2. J: diferencia por la forma de agregar la TPM (decisión 1); máximo 0,15 p.p. en 2022-IV.
